qichacha/__init__.py
qichacha/client.py
qichacha/exceptions.py
qichacha-0.0.9.dist-info/LICENSE
qichacha-0.0.9.dist-info/METADATA
qichacha-0.0.9.dist-info/WHEEL
qichacha-0.0.9.dist-info/top_level.txt
qichacha-0.0.9.dist-info/RECORD
