Metadata-Version: 2.1
Name: qichacha
Version: 0.0.9
Summary: 企查查的api
Home-page: https://github.com/ramwin/qichacha
Author: Xiang Wang
Author-email: ramwin@qq.com
License: UNKNOWN
Platform: UNKNOWN
Classifier: Programming Language :: Python :: 3
Classifier: License :: OSI Approved :: MIT License
Classifier: Operating System :: OS Independent
